ADPTC_LIB/DPTree.py
ADPTC_LIB/DPTree_ST.py
ADPTC_LIB/__init__.py
ADPTC_LIB/cluster.py
ADPTC_LIB/context.py
ADPTC_LIB/myutil.py
ADPTC_LIB/prepare.py
ADPTC_LIB/visual.py
ADPTC_LIB-0.0.4.dist-info/LICENSE
ADPTC_LIB-0.0.4.dist-info/METADATA
ADPTC_LIB-0.0.4.dist-info/WHEEL
ADPTC_LIB-0.0.4.dist-info/top_level.txt
ADPTC_LIB-0.0.4.dist-info/RECORD
