Metadata-Version: 2.1
Name: ADPTC-LIB
Version: 0.0.4
Summary: 自适应密度峰值树聚类（Adaptive Density Peak Tree Clustering）
Home-page: UNKNOWN
Author: SongJ
Author-email: songjie0613@126.com
License: UNKNOWN
Platform: UNKNOWN
Classifier: Programming Language :: Python :: 3
Classifier: License :: OSI Approved :: MIT License
Classifier: Operating System :: OS Independent
Requires-Python: >=3.6
